youtube_to_audio/__init__.py
youtube_to_audio/cli.py
youtube_to_audio/downloader.py
youtube_to_audio-0.1.7.dist-info/LICENSE
youtube_to_audio-0.1.7.dist-info/METADATA
youtube_to_audio-0.1.7.dist-info/WHEEL
youtube_to_audio-0.1.7.dist-info/entry_points.txt
youtube_to_audio-0.1.7.dist-info/top_level.txt
youtube_to_audio-0.1.7.dist-info/RECORD
