Metadata-Version: 2.2
Name: youtube-to-audio
Version: 0.1.7
Summary: A lightweight Python package and CLI tool that extracts audio from YouTube videos in multiple formats.
Author-email: Jack Tol <contact@jacktol.net>
License: MIT
Project-URL: Homepage, https://github.com/jack-tol/youtube-to-audio
Project-URL: Repository, https://github.com/jack-tol/youtube-to-audio
Requires-Python: >=3.6
License-File: LICENSE
Requires-Dist: yt-dlp
Requires-Dist: click
